{"statusCode": 200, "body": "{\"submission_id\": \"sub_1746325257888_0579fa98-9c49-4ca7-910b-f169408946fc\", \"problem_id\": \"sample-problem-add-two\", \"language\": \"python\", \"status\": \"RUNTIME_ERROR\", \"execution_time\": 0.0979, \"results\": [{\"case\": 1, \"status\": \"RUNTIME_ERROR\", \"execution_time\": 0.0979}], \"submission_time\": 1746325257, \"user_code\": \"# Example: Read two integers from input and print their sum\\ntry:\\n    a, b = map(int, input().split())\\n    print(a + b)\\nexcept Exception as e:\\n    # It's good practice for competitive programming solutions\\n    # to handle potential input errors gracefully, though not always required.\\n    import sys\\n    print(f\\\\\\\"Error processing input: {e}\\\\\\\", file=sys.stderr)\\n\", \"error_message\": \"Case 1: Runtime Error. Details in runner logs or S3 result.\"}"}